{
    "lines": [
        {
            "type": "text",
            "characterName": null,
            "text": "<i>Pasas el bono por la máquina y sale una luz roja.<i>",
            "pause": true,
            "imageAssetId": null
        },
        {
            "type": "text",
            "characterName": "El Kike",
            "text": "Venga tío, que se supone que me estás persiguiendo.",
            "pause": true,
            "imageAssetId": "Portraits/Punk"
        },
        {
            "type": "text",
            "characterName": "Juan",
            "text": "No tengo cargado el bono...",
            "pause": true,
            "imageAssetId": "Portraits/Boy"
        },
        {
            "type": "text",
            "characterName": "Ladrón",
            "text": "Bro, háztelo mirar...",
            "pause": true,
            "imageAssetId": "Portraits/Punk"
        },
        {
            "type": "notification",
            "notificationId": "Return",
            "text": "Return"
        },
        {
            "type": "text",
            "characterName": "Juan",
            "text": "<i>Debería recargarlo en la máquina...<i>",
            "pause": true,
            "imageAssetId": "Portraits/Boy"
        },
        {
            "type": "notification",
            "notificationId": "Bono2",
            "text": "Bono2"
        }
    ]
}