{
    "lines": [
        {
            "type": "text",
            "characterName": "Chavala",
            "text": "¿Qué, ya tienes el cómic?",
            "pause": true,
            "imageAssetId": "IMGChavala"
        },
        {
            "type": "text",
            "characterName": "Juan",
            "text": "No, todavía no.",
            "pause": true,
            "imageAssetId": "IMGJuan"
        },
        {
            "type": "text",
            "characterName": "Chavala",
            "text": "Pues estás tardando.",
            "pause": true,
            "imageAssetId": "IMGChavala"
        },
        {
            "type": "text",
            "characterName": "Chavala",
            "text": "Lo tiene el viejo del quiosco.",
            "pause": true,
            "imageAssetId": "IMGChavala"
        }
    ]
}