{
    "lines": [
        {
            "type": "text",
            "characterName": "Chavala",
            "text": "¿Chat, quién ha invitado a este tío?",
            "pause": true,
            "imageAssetId": "IMGChavala"
        },
        {
            "type": "text",
            "characterName": "Chavala",
            "text": "Fuera de aquí o te metro otro permaban.",
            "pause": true,
            "imageAssetId": "IMGChavala"
        },
        {
            "type": "notification",
            "notificationId": "ChavalaIgnoresJuanDialogueFinished",
            "text": "ChavalaIgnoresJuanFinished"
        }
    ]
}