{
    "lines": [
        {
            "type": "text",
            "characterName": "Kas",
            "text": "Eh tú, dile al chaval lo que necesita saber.",
            "pause": true,
            "imageAssetId": "Portraits/old_man"
        },
        {
            "type": "text",
            "characterName": "Maruja",
            "text": "¿Y mi ropa qué?",
            "pause": true,
            "imageAssetId": "Portraits/Lady"
        },
        {
            "type": "text",
            "characterName": "Kas",
            "text": "Ahora te la recojo yo, díselo.",
            "pause": true,
            "imageAssetId": "Portraits/old_man"
        },
        {
            "type": "text",
            "characterName": "Maruja",
            "text": "Bueno venga te lo cuento, yo soy amiga de la madre de ese chico.",
            "pause": true,
            "imageAssetId": "Portraits/Lady"
        },
        {
            "type": "text",
            "characterName": "Maruja",
            "text": "Se llama <color=red>Kike</color> y se meaba en la cama hasta hace bien poco.",
            "pause": true,
            "imageAssetId": "Portraits/Lady"
        },
        {
            "type": "text",
            "characterName": "Juan",
            "text": "<i>Me pregunto si esa <color=yellow>información</color> será útil...</i>",
            "pause": true,
            "imageAssetId": "Portraits/Boy"
        },
        {
            "type": "notification",
            "notificationId": "MarujaDialogueFinished",
            "text": "NPCs/MarujaMinigameSkippedRepeat"
        }
    ]
}